{
  "placeholderImages": [
    {
      "id": "avatar-1",
      "description": "Avatar for Ana Silva",
      "imageUrl": "https://picsum.photos/seed/1/100/100",
      "imageHint": "woman avatar"
    },
    {
      "id": "avatar-2",
      "description": "Avatar for Bruno Costa",
      "imageUrl": "https://picsum.photos/seed/2/100/100",
      "imageHint": "man avatar"
    },
    {
      "id": "avatar-3",
      "description": "Avatar for Carla Dias",
      "imageUrl": "https://picsum.photos/seed/3/100/100",
      "imageHint": "woman avatar"
    },
    {
      "id": "avatar-4",
      "description": "Avatar for Daniel Martins",
      "imageUrl": "https://picsum.photos/seed/4/100/100",
      "imageHint": "man avatar"
    },
    {
      "id": "avatar-5",
      "description": "Avatar for user profile",
      "imageUrl": "https://picsum.photos/seed/99/100/100",
      "imageHint": "person avatar"
    }
  ]
}